sdb2xml/__init__.py
sdb2xml/__main__.py
sdb2xml/apphelp.py
sdb2xml/cli.py
sdb2xml-0.2.0.dist-info/METADATA
sdb2xml-0.2.0.dist-info/WHEEL
sdb2xml-0.2.0.dist-info/entry_points.txt
sdb2xml-0.2.0.dist-info/licenses/LICENSE.txt
sdb2xml-0.2.0.dist-info/RECORD
