Metadata-Version: 2.4
Name: sdb2xml
Version: 0.2.0
Summary: Dump SDB file to xml using apphelp.dll
Project-URL: Homepage, https://pypi.org/project/sdb2xml/
Project-URL: Changelog, https://github.com/learn-more/sdb2xml/releases
Project-URL: Issues, https://github.com/learn-more/sdb2xml/issues
Project-URL: CI, https://github.com/learn-more/sdb2xml/actions
Project-URL: Repository, https://github.com/learn-more/sdb2xml
Author-email: Mark Jansen <mark.jansen@reactos.org>
License-Expression: MIT
License-File: LICENSE.txt
Keywords: appcompat,apphelp,sdb,sdb2xml,shim,shimeng
Classifier: Development Status :: 3 - Alpha
Classifier: Environment :: Console
Classifier: Operating System :: Microsoft :: Windows
Classifier: Programming Language :: Python :: 3
Classifier: Topic :: Utilities
Requires-Python: >=3.10
Requires-Dist: click>=8.2.1
